bucket_dir/__init__.py
bucket_dir/folder.py
bucket_dir/generator.py
bucket_dir/index.py
bucket_dir/s3_gateway.py
bucket_dir/templates/index.html.j2
bucket_dir-3.2.0.dist-info/entry_points.txt
bucket_dir-3.2.0.dist-info/LICENSE
bucket_dir-3.2.0.dist-info/WHEEL
bucket_dir-3.2.0.dist-info/METADATA
bucket_dir-3.2.0.dist-info/RECORD
