Metadata-Version: 2.1
Name: bucket-dir
Version: 3.2.0
Summary: Generate directory listings for S3 statically hosted content.
Home-page: https://github.com/hmrc/bucket-dir
License: Apache-2.0
Author: Dave Randall
Author-email: 19395688+daveygit2050@users.noreply.github.com
Requires-Python: >=3.7,<4.0
Classifier: License :: OSI Approved :: Apache Software License
Classifier: Programming Language :: Python :: 3
Classifier: Programming Language :: Python :: 3.10
Classifier: Programming Language :: Python :: 3.7
Classifier: Programming Language :: Python :: 3.8
Classifier: Programming Language :: Python :: 3.9
Requires-Dist: Jinja2
Requires-Dist: boto3
Requires-Dist: click
Requires-Dist: humanize
Project-URL: Repository, https://github.com/hmrc/bucket-dir
